{
    "caption": "Dancing letters",
    "duration": 4000,
    "options": [
        [
            {
                "name": "text",
                "caption": "Text",
                "type": "text",
                "value": "Dancing letters",
                "quotes": true
            },
            {
                "name": "letter_color1",
                "caption": "Letter color 1",
                "type": "color",
                "value": "#FF1461",
                "quotes": true
            },
            {
                "name": "letter_color2",
                "caption": "Letter color 2",
                "type": "color",
                "value": "#18FF92",
                "quotes": true
            },
            {
                "name": "letter_color3",
                "caption": "Letter color 3",
                "type": "color",
                "value": "#5A87FF",
                "quotes": true
            },
            {
                "name": "letter_color4",
                "caption": "Letter color 4",
                "type": "color",
                "value": "#FBF38C",
                "quotes": true
            }
        ]
    ]
}